{"location":"Palo Alto and SF, usually.","default_profile":false,"statuses_count":247,"profile_background_tile":true,"lang":"en","profile_link_color":"0084B4","id":10961632,"following":false,"favourites_count":13,"protected":false,"profile_text_color":"333333","description":"I design. I teach. I research.","verified":false,"contributors_enabled":false,"profile_sidebar_border_color":"C0DEED","name":"Wendy Ju","profile_background_color":"C0DEED","created_at":"Sat Dec 08 04:47:38 +0000 2007","default_profile_image":false,"followers_count":349,"profile_image_url_https":"https:\/\/si0.twimg.com\/profile_images\/1908191181\/wendyface_normal.gif","geo_enabled":false,"status":{"contributors":null,"text":"According to my alarm clock, tonight I'm going to dream that I created a rift in the space-time continuum by meeting my future self...","geo":null,"retweeted":false,"in_reply_to_screen_name":null,"truncated":false,"lang":"en","entities":{"symbols":[],"urls":[],"hashtags":[],"user_mentions":[]},"in_reply_to_status_id_str":null,"id":369822048370978816,"source":"<a href=\"https:\/\/itunes.apple.com\/us\/app\/carrot-alarm\/id623700355?mt=8&uo=4\" rel=\"nofollow\">CARROT Alarm on iOS<\/a>","in_reply_to_user_id_str":null,"favorited":false,"in_reply_to_status_id":null,"in_reply_to_user_id":null,"created_at":"Tue Aug 20 14:03:41 +0000 2013","retweet_count":0,"favorite_count":0,"id_str":"369822048370978816","place":null,"coordinates":null},"profile_background_image_url":"http:\/\/a0.twimg.com\/profile_background_images\/452518495\/b.gif","profile_background_image_url_https":"https:\/\/si0.twimg.com\/profile_background_images\/452518495\/b.gif","entities":{"description":{"urls":[]},"url":{"urls":[{"expanded_url":"http:\/\/wendyju.com","indices":[0,22],"display_url":"wendyju.com","url":"http:\/\/t.co\/zcQ47f4vlA"}]}},"follow_request_sent":false,"url":"http:\/\/t.co\/zcQ47f4vlA","utc_offset":-25200,"time_zone":"Pacific Time (US & Canada)","notifications":false,"friends_count":174,"profile_use_background_image":true,"profile_sidebar_fill_color":"DDEEF6","screen_name":"wendyju","id_str":"10961632","profile_image_url":"http:\/\/a0.twimg.com\/profile_images\/1908191181\/wendyface_normal.gif","is_translator":false,"listed_count":17}