{"location":"Peckham, Copenhagen, New York","default_profile":false,"statuses_count":2829,"profile_background_tile":true,"lang":"en","profile_link_color":"38374A","profile_banner_url":"https:\/\/pbs.twimg.com\/profile_banners\/7682702\/1378201541","id":7682702,"following":false,"favourites_count":325,"protected":false,"profile_text_color":"451F38","description":"Business anthropologist, also running @epiconference 2013. Not a writer of twitter profiles.","verified":false,"contributors_enabled":false,"profile_sidebar_border_color":"6CAB6C","name":"Simon Roberts","profile_background_color":"45002D","created_at":"Tue Jul 24 13:07:52 +0000 2007","default_profile_image":false,"followers_count":740,"profile_image_url_https":"https:\/\/si0.twimg.com\/profile_images\/1273299357\/vintage-simon-electronic-game-works_370483463210_normal.jpg","geo_enabled":true,"status":{"contributors":null,"text":"The medal for best summarising of #epic2013 on a blog -&gt; @JamesAsterisk   http:\/\/t.co\/IjH34y1mqX - a great service to attendees &amp; others","geo":null,"retweeted":false,"in_reply_to_screen_name":null,"possibly_sensitive":false,"truncated":false,"lang":"en","entities":{"symbols":[],"urls":[{"expanded_url":"http:\/\/jamesasterisk.wordpress.com\/","indices":[77,99],"display_url":"jamesasterisk.wordpress.com","url":"http:\/\/t.co\/IjH34y1mqX"}],"hashtags":[{"text":"epic2013","indices":[34,43]}],"user_mentions":[{"id":19864220,"name":"James Turner","indices":[60,74],"screen_name":"JamesAsterisk","id_str":"19864220"}]},"in_reply_to_status_id_str":null,"id":379992247367761920,"in_reply_to_user_id_str":null,"source":"<a href=\"http:\/\/www.tweetdeck.com\" rel=\"nofollow\">TweetDeck<\/a>","favorited":false,"in_reply_to_status_id":null,"in_reply_to_user_id":null,"created_at":"Tue Sep 17 15:36:26 +0000 2013","retweet_count":9,"favorite_count":3,"id_str":"379992247367761920","place":null,"coordinates":null},"profile_background_image_url":"http:\/\/a0.twimg.com\/profile_background_images\/58133452\/x00de7c5293110ed07aa56e478b6d9bf.png","profile_background_image_url_https":"https:\/\/si0.twimg.com\/profile_background_images\/58133452\/x00de7c5293110ed07aa56e478b6d9bf.png","entities":{"description":{"urls":[]},"url":{"urls":[{"expanded_url":"http:\/\/www.ideasbazaar.com","indices":[0,22],"display_url":"ideasbazaar.com","url":"http:\/\/t.co\/sebQcLmcsc"}]}},"follow_request_sent":false,"url":"http:\/\/t.co\/sebQcLmcsc","utc_offset":3600,"time_zone":"London","notifications":false,"friends_count":345,"profile_use_background_image":true,"profile_sidebar_fill_color":"3A8577","screen_name":"ideasbazaar","id_str":"7682702","profile_image_url":"http:\/\/a0.twimg.com\/profile_images\/1273299357\/vintage-simon-electronic-game-works_370483463210_normal.jpg","is_translator":false,"listed_count":32}