{"location":"London","default_profile":true,"statuses_count":1330,"profile_background_tile":false,"lang":"en","profile_link_color":"0084B4","id":14821014,"following":false,"favourites_count":14,"protected":false,"profile_text_color":"333333","description":"Remy Bourganel, Director, exploratory design research, Orange UI program, Orange. Ensad, head of interaction+service design course, EnsadLab IDM founder.","verified":false,"contributors_enabled":false,"profile_sidebar_border_color":"C0DEED","name":"epourkoapa","profile_background_color":"C0DEED","created_at":"Sun May 18 14:27:50 +0000 2008","default_profile_image":false,"followers_count":329,"profile_image_url_https":"https:\/\/si0.twimg.com\/profile_images\/319608897\/1DS_2743_light_1_normal.jpg","geo_enabled":true,"status":{"contributors":null,"text":"\"Le Front national sera majoritaire\", pr?dit le philosophe Bernard Stiegler - L'EXPRESS http:\/\/t.co\/2ESeNltw3A via @Lexpress","geo":null,"retweeted":false,"in_reply_to_screen_name":null,"possibly_sensitive":false,"truncated":false,"lang":"fr","entities":{"symbols":[],"urls":[{"expanded_url":"http:\/\/po.st\/a65iXi","indices":[88,110],"display_url":"po.st\/a65iXi","url":"http:\/\/t.co\/2ESeNltw3A"}],"hashtags":[],"user_mentions":[{"id":13353862,"name":"LEXPRESS","indices":[115,124],"screen_name":"LEXPRESS","id_str":"13353862"}]},"in_reply_to_status_id_str":null,"id":378297876335456256,"in_reply_to_user_id_str":null,"source":"<a href=\"http:\/\/twitter.com\/tweetbutton\" rel=\"nofollow\">Tweet Button<\/a>","favorited":false,"in_reply_to_status_id":null,"in_reply_to_user_id":null,"created_at":"Thu Sep 12 23:23:36 +0000 2013","retweet_count":2,"favorite_count":0,"id_str":"378297876335456256","place":null,"coordinates":null},"profile_background_image_url":"http:\/\/abs.twimg.com\/images\/themes\/theme1\/bg.png","profile_background_image_url_https":"https:\/\/abs.twimg.com\/images\/themes\/theme1\/bg.png","entities":{"description":{"urls":[]},"url":{"urls":[{"expanded_url":"http:\/\/epourkoapa.wordpress.com\/","indices":[0,22],"display_url":"epourkoapa.wordpress.com","url":"http:\/\/t.co\/aYZprhkEkv"}]}},"follow_request_sent":false,"url":"http:\/\/t.co\/aYZprhkEkv","utc_offset":7200,"time_zone":"Paris","notifications":false,"friends_count":460,"profile_use_background_image":true,"profile_sidebar_fill_color":"DDEEF6","screen_name":"epourkoapa","id_str":"14821014","profile_image_url":"http:\/\/a0.twimg.com\/profile_images\/319608897\/1DS_2743_light_1_normal.jpg","is_translator":false,"listed_count":30}