{"location":"Endoume, Marseille","default_profile":false,"statuses_count":258,"profile_background_tile":true,"lang":"en","profile_link_color":"876C00","profile_banner_url":"https:\/\/pbs.twimg.com\/profile_banners\/68812552\/1379408537","id":68812552,"following":false,"favourites_count":22,"protected":false,"profile_text_color":"333333","description":".SE ex-pat musician\/producer, A\/R for Data Airlines and making chiptunes for Razor 1911.","verified":false,"contributors_enabled":false,"profile_sidebar_border_color":"000000","name":"Dubmood","profile_background_color":"000000","created_at":"Tue Aug 25 21:47:30 +0000 2009","default_profile_image":false,"followers_count":532,"profile_image_url_https":"https:\/\/si0.twimg.com\/profile_images\/378800000001259915\/60a124b4c01fc5f86a81ec48f7815de8_normal.jpeg","geo_enabled":false,"status":{"contributors":null,"text":"So what do you guys think of the simple machine track &amp; video? I know its not pure chiptune but I thought LF2 would calm that need for blip","geo":null,"retweeted":false,"in_reply_to_screen_name":null,"truncated":false,"lang":"en","entities":{"symbols":[],"urls":[],"hashtags":[],"user_mentions":[]},"in_reply_to_status_id_str":null,"id":380026475258191872,"source":"web","in_reply_to_user_id_str":null,"favorited":false,"in_reply_to_status_id":null,"in_reply_to_user_id":null,"created_at":"Tue Sep 17 17:52:26 +0000 2013","retweet_count":0,"favorite_count":0,"id_str":"380026475258191872","place":null,"coordinates":null},"profile_background_image_url":"http:\/\/a0.twimg.com\/profile_background_images\/378800000000157001\/77512c24c8de914d271c39fde02b4152.jpeg","profile_background_image_url_https":"https:\/\/si0.twimg.com\/profile_background_images\/378800000000157001\/77512c24c8de914d271c39fde02b4152.jpeg","entities":{"description":{"urls":[]},"url":{"urls":[{"expanded_url":"http:\/\/www.dataairlines.net\/dubmood","indices":[0,22],"display_url":"dataairlines.net\/dubmood","url":"http:\/\/t.co\/vzH1lbF6ia"}]}},"follow_request_sent":false,"url":"http:\/\/t.co\/vzH1lbF6ia","utc_offset":null,"time_zone":null,"notifications":false,"friends_count":59,"profile_use_background_image":true,"profile_sidebar_fill_color":"DDEEF6","screen_name":"dubmood","id_str":"68812552","profile_image_url":"http:\/\/a0.twimg.com\/profile_images\/378800000001259915\/60a124b4c01fc5f86a81ec48f7815de8_normal.jpeg","is_translator":false,"listed_count":26}